<?xml version="1.0" encoding="UTF-8"?><record_update sys_domain="global" table="sys_ux_page_property">
    <sys_ux_page_property action="DELETE">
        <choices/>
        <description/>
        <name>chrome_header</name>
        <page display_value="EA Engagement Portal">192cc919c7828110ea4c8c668d10c860</page>
        <required_translations>[]</required_translations>
        <route display_value="Landing Page">512cc9199882811091b47f267e2f3f6c</route>
        <suffix/>
        <sys_class_name>sys_ux_page_property</sys_class_name>
        <sys_created_by>system</sys_created_by>
        <sys_created_on>2022-03-04 08:33:48</sys_created_on>
        <sys_domain>global</sys_domain>
        <sys_domain_path>global</sys_domain_path>
        <sys_id>552cc91948828110a9de93102430dd62</sys_id>
        <sys_mod_count>0</sys_mod_count>
        <sys_name>chrome_header</sys_name>
        <sys_package display_value="EA Engagement" source="x_513020_ea_enga_0">d1a47fb82f8e011086f2b8e72799b6bf</sys_package>
        <sys_policy/>
        <sys_scope display_value="EA Engagement">d1a47fb82f8e011086f2b8e72799b6bf</sys_scope>
        <sys_update_name>sys_ux_page_property_552cc91948828110a9de93102430dd62</sys_update_name>
        <sys_updated_by>system</sys_updated_by>
        <sys_updated_on>2022-03-04 08:33:48</sys_updated_on>
        <type>json</type>
        <unique_name>x_513020_ea_enga_0.192cc919c7828110ea4c8c668d10c860.route.chrome_header.512cc9199882811091b47f267e2f3f6c</unique_name>
        <value>{&#13;
    "privatePage":{&#13;
       "searchEnabled": false&#13;
    }&#13;
}</value>
    </sys_ux_page_property>
    <sys_translated_text action="DELETE" query="documentkey=552cc91948828110a9de93102430dd62"/>
<sys_update_version action="INSERT_OR_UPDATE">
        <action>DELETE</action>
        <application display_value="EA Engagement">d1a47fb82f8e011086f2b8e72799b6bf</application>
        <file_path/>
        <instance_id>cc5ad55fdbaf5f887d8cf22ebf961978</instance_id>
        <instance_name>dev68328</instance_name>
        <name>sys_ux_page_property_552cc91948828110a9de93102430dd62</name>
        <payload><![CDATA[<?xml version="1.0" encoding="UTF-8"?><record_update sys_domain="global" table="sys_ux_page_property">
    <sys_ux_page_property action="INSERT_OR_UPDATE">
        <choices/>
        <description/>
        <name>chrome_header</name>
        <page display_value="EA Engagement Portal">192cc919c7828110ea4c8c668d10c860</page>
        <required_translations>[]</required_translations>
        <route display_value="Landing Page">512cc9199882811091b47f267e2f3f6c</route>
        <suffix/>
        <sys_class_name>sys_ux_page_property</sys_class_name>
        <sys_created_by>system</sys_created_by>
        <sys_created_on>2022-03-04 08:33:48</sys_created_on>
        <sys_domain>global</sys_domain>
        <sys_domain_path>global</sys_domain_path>
        <sys_id>552cc91948828110a9de93102430dd62</sys_id>
        <sys_mod_count>0</sys_mod_count>
        <sys_name>chrome_header</sys_name>
        <sys_package display_value="EA Engagement" source="x_513020_ea_enga_0">d1a47fb82f8e011086f2b8e72799b6bf</sys_package>
        <sys_policy/>
        <sys_scope display_value="EA Engagement">d1a47fb82f8e011086f2b8e72799b6bf</sys_scope>
        <sys_update_name>sys_ux_page_property_552cc91948828110a9de93102430dd62</sys_update_name>
        <sys_updated_by>system</sys_updated_by>
        <sys_updated_on>2022-03-04 08:33:48</sys_updated_on>
        <type>json</type>
        <unique_name>x_513020_ea_enga_0.192cc919c7828110ea4c8c668d10c860.route.chrome_header.512cc9199882811091b47f267e2f3f6c</unique_name>
        <value>{&#13;
    "privatePage":{&#13;
       "searchEnabled": false&#13;
    }&#13;
}</value>
    </sys_ux_page_property>
    <sys_translated_text action="delete_multiple" query="documentkey=552cc91948828110a9de93102430dd62"/>
</record_update>]]></payload>
        <payload_hash>-693880990</payload_hash>
        <record_name>chrome_header</record_name>
        <reverted_from/>
        <source>3b6a078a2f82011086f2b8e72799b611</source>
        <source_table>sys_upgrade_history</source_table>
        <state>previous</state>
        <sys_created_by>admin</sys_created_by>
        <sys_created_on>2022-03-07 01:41:35</sys_created_on>
        <sys_id>559a03ca2f82011086f2b8e72799b60d</sys_id>
        <sys_mod_count>0</sys_mod_count>
        <sys_recorded_at>17f6209f9c90000001</sys_recorded_at>
        <sys_updated_by>admin</sys_updated_by>
        <sys_updated_on>2022-03-07 01:41:35</sys_updated_on>
        <type>UX Page Property</type>
        <update_guid>919a03cae8820110859488447b27840d</update_guid>
        <update_guid_history>919a03cae8820110859488447b27840d:0,ca9366e1a2020110c5f070e451fc674e:759722976,429366e1f2020110a273c93768d2753f:-1578166471</update_guid_history>
    </sys_update_version>
    <sys_metadata_delete action="INSERT_OR_UPDATE">
        <sys_audit_delete/>
        <sys_class_name>sys_metadata_delete</sys_class_name>
        <sys_created_by>admin</sys_created_by>
        <sys_created_on>2022-03-07 01:50:17</sys_created_on>
        <sys_db_object display_value="" name="sys_ux_page_property">sys_ux_page_property</sys_db_object>
        <sys_id>430c8248eabc4bb8a693b7d390d79640</sys_id>
        <sys_metadata>552cc91948828110a9de93102430dd62</sys_metadata>
        <sys_mod_count>0</sys_mod_count>
        <sys_name>chrome_header</sys_name>
        <sys_package display_value="EA Engagement" source="x_513020_ea_enga_0">d1a47fb82f8e011086f2b8e72799b6bf</sys_package>
        <sys_parent/>
        <sys_policy/>
        <sys_scope display_value="EA Engagement">d1a47fb82f8e011086f2b8e72799b6bf</sys_scope>
        <sys_scope_delete display_value="">3c73c119632544ccb51dcfea68920610</sys_scope_delete>
        <sys_update_name>sys_ux_page_property_552cc91948828110a9de93102430dd62</sys_update_name>
        <sys_update_version display_value="sys_ux_page_property_552cc91948828110a9de93102430dd62">559a03ca2f82011086f2b8e72799b60d</sys_update_version>
        <sys_updated_by>admin</sys_updated_by>
        <sys_updated_on>2022-03-07 01:50:17</sys_updated_on>
    </sys_metadata_delete>
</record_update>
